monomorphic/__init__.py
monomorphic-0.1.9.dist-info/AUTHORS
monomorphic-0.1.9.dist-info/LICENSE
monomorphic-0.1.9.dist-info/METADATA
monomorphic-0.1.9.dist-info/WHEEL
monomorphic-0.1.9.dist-info/top_level.txt
monomorphic-0.1.9.dist-info/RECORD
